umacajadada/README.MD
umacajadada/__init__.py
umacajadada/requirements.txt
umacajadada/thirdparty.json
umacajadada-0.11.dist-info/LICENSE.rst
umacajadada-0.11.dist-info/METADATA
umacajadada-0.11.dist-info/WHEEL
umacajadada-0.11.dist-info/top_level.txt
umacajadada-0.11.dist-info/RECORD
