Metadata-Version: 2.1
Name: umacajadada
Version: 0.11
Summary: reads a file asynchronously during its execution while somewhere some other process writes to the same file
Home-page: https://github.com/hansalemaos/umacajadada
Author: Johannes Fischer
Author-email: aulasparticularesdealemaosp@gmail.com
License: MIT
Keywords: read,write,same,time
Classifier: Development Status :: 4 - Beta
Classifier: Programming Language :: Python :: 3 :: Only
Classifier: Programming Language :: Python :: 3.10
Classifier: Topic :: Software Development :: Libraries :: Python Modules
Classifier: Topic :: Utilities
License-File: LICENSE.rst
Requires-Dist: kthread
